{
  "app.html": "app.html?v=b96d774f53",
  "bill.html": "bill.html?v=89f9075bb7",
  "billdetail.html": "billdetail.html?v=82594af855",
  "contract.html": "contract.html?v=72943d945d",
  "count.html": "count.html?v=64e91db2c9",
  "customer.html": "customer.html?v=e7f112c9a4",
  "customersel.html": "customersel.html?v=d77b18a66f",
  "delete-label.html": "delete-label.html?v=a754171810",
  "delete.html": "delete.html?v=bc9bc8bd0f",
  "desktop.html": "desktop.html?v=d54265ca8d",
  "device - 副本.html": "device - 副本.html?v=3cfde1a4a0",
  "device.html": "device.html?v=0cd2a83144",
  "employee.html": "employee.html?v=1f271a2364",
  "error.html": "error.html?v=a683bbdf3a",
  "grant.html": "grant.html?v=79b11301dc",
  "historyAdd.html": "historyAdd.html?v=805981d587",
  "historyLook.html": "historyLook.html?v=c88d6edec3",
  "log.html": "log.html?v=19c62b139d",
  "login.html": "login.html?v=1d38fa7631",
  "message.html": "message.html?v=8d7c5ca54e",
  "message2.html": "message2.html?v=e0159c24f3",
  "nav.html": "nav.html?v=5f22581130",
  "ownercenter.html": "ownercenter.html?v=b4c69b2508",
  "property.html": "property.html?v=84d305e6bd",
  "report.html": "report.html?v=139cbf473d",
  "resetpwd.html": "resetpwd.html?v=18dbc30868",
  "self.html": "self.html?v=f27009d7fd",
  "system.html": "system.html?v=f25a443c88"
}